ffrich.py
ffrich-0.2.1.dist-info/COPYING
ffrich-0.2.1.dist-info/METADATA
ffrich-0.2.1.dist-info/WHEEL
ffrich-0.2.1.dist-info/entry_points.txt
ffrich-0.2.1.dist-info/top_level.txt
ffrich-0.2.1.dist-info/zip-safe
ffrich-0.2.1.dist-info/RECORD
