Metadata-Version: 2.1
Name: ffrich
Version: 0.2.1
Summary: A simple progress bar for ffmpeg, written in Python using rich
Home-page: https://github.com/banksio/ffrich
Author: banksio
Author-email: nathantb3@gmail.com
License: MIT
Project-URL: Bug Tracker, https://github.com/banksio/ffrich/issues
Project-URL: Changelog, https://github.com/banksio/ffrich/blob/master/CHANGELOG.md
Keywords: ffmpeg,ffmpeg-command,progress-bar,python-script,cli
Platform: any
Classifier: Development Status :: 4 - Beta
Classifier: Environment :: Console
Classifier: License :: OSI Approved :: MIT License
Classifier: Operating System :: Microsoft :: Windows
Classifier: Operating System :: Unix
Classifier: Programming Language :: Python
Classifier: Programming Language :: Python :: 3.9
Classifier: Programming Language :: Python :: 3.10
Classifier: Programming Language :: Python :: 3.11
Classifier: Programming Language :: Python :: 3.12
Classifier: Programming Language :: Python :: 3.13
Classifier: Topic :: Multimedia :: Video :: Conversion
Requires-Python: >=3.9
License-File: COPYING
Requires-Dist: rich <14.0,>=10.0
